acquire/__init__.py
acquire/acquire.py
acquire/collector.py
acquire/crypt.py
acquire/esxi.py
acquire/hashes.py
acquire/log.py
acquire/utils.py
acquire/version.py
acquire/volatilestream.py
acquire/dynamic/__init__.py
acquire/dynamic/windows/__init__.py
acquire/dynamic/windows/collect.py
acquire/dynamic/windows/exceptions.py
acquire/dynamic/windows/handles.py
acquire/dynamic/windows/named_objects.py
acquire/dynamic/windows/ntdll.py
acquire/dynamic/windows/types.py
acquire/gui/__init__.py
acquire/gui/base.py
acquire/gui/win32.py
acquire/outputs/__init__.py
acquire/outputs/base.py
acquire/outputs/dir.py
acquire/outputs/tar.py
acquire/outputs/zip.py
acquire/tools/__init__.py
acquire/tools/decrypter.py
acquire/uploaders/__init__.py
acquire/uploaders/minio.py
acquire/uploaders/plugin.py
acquire/uploaders/plugin_registry.py
acquire-3.20.1.dist-info/licenses/COPYRIGHT
acquire-3.20.1.dist-info/licenses/LICENSE
acquire-3.20.1.dist-info/METADATA
acquire-3.20.1.dist-info/WHEEL
acquire-3.20.1.dist-info/entry_points.txt
acquire-3.20.1.dist-info/top_level.txt
acquire-3.20.1.dist-info/RECORD
